django_mongodb_backend/__init__.py
django_mongodb_backend/aggregates.py
django_mongodb_backend/base.py
django_mongodb_backend/checks.py
django_mongodb_backend/client.py
django_mongodb_backend/compiler.py
django_mongodb_backend/creation.py
django_mongodb_backend/dbapi.py
django_mongodb_backend/features.py
django_mongodb_backend/functions.py
django_mongodb_backend/indexes.py
django_mongodb_backend/introspection.py
django_mongodb_backend/lookups.py
django_mongodb_backend/managers.py
django_mongodb_backend/models.py
django_mongodb_backend/operations.py
django_mongodb_backend/query.py
django_mongodb_backend/query_utils.py
django_mongodb_backend/queryset.py
django_mongodb_backend/routers.py
django_mongodb_backend/schema.py
django_mongodb_backend/test.py
django_mongodb_backend/transaction.py
django_mongodb_backend/utils.py
django_mongodb_backend/validation.py
django_mongodb_backend/validators.py
django_mongodb_backend/expressions/__init__.py
django_mongodb_backend/expressions/builtins.py
django_mongodb_backend/expressions/expressions.py
django_mongodb_backend/expressions/search.py
django_mongodb_backend/fields/__init__.py
django_mongodb_backend/fields/array.py
django_mongodb_backend/fields/auto.py
django_mongodb_backend/fields/duration.py
django_mongodb_backend/fields/embedded_model.py
django_mongodb_backend/fields/embedded_model_array.py
django_mongodb_backend/fields/json.py
django_mongodb_backend/fields/objectid.py
django_mongodb_backend/fields/polymorphic_embedded_model.py
django_mongodb_backend/fields/polymorphic_embedded_model_array.py
django_mongodb_backend/fields/utils.py
django_mongodb_backend/forms/__init__.py
django_mongodb_backend/forms/fields/__init__.py
django_mongodb_backend/forms/fields/array.py
django_mongodb_backend/forms/fields/embedded_model.py
django_mongodb_backend/forms/fields/embedded_model_array.py
django_mongodb_backend/forms/fields/objectid.py
django_mongodb_backend/gis/__init__.py
django_mongodb_backend/gis/adapter.py
django_mongodb_backend-6.0.0.dist-info/METADATA
django_mongodb_backend-6.0.0.dist-info/WHEEL
django_mongodb_backend-6.0.0.dist-info/licenses/LICENSE
django_mongodb_backend-6.0.0.dist-info/RECORD
