Metadata-Version: 2.4
Name: django-mongodb-backend
Version: 6.0.0
Summary: Django MongoDB Backend
Project-URL: Homepage, https://www.mongodb.org
Project-URL: Documentation, https://django-mongodb-backend.readthedocs.io
Project-URL: Source, https://github.com/mongodb/django-mongodb-backend
Project-URL: Tracker, https://github.com/mongodb/django-mongodb-backend/issues
Author: The MongoDB Python Team
License:                                  Apache License
License-File: LICENSE
Keywords: django,mongo,mongodb,pymongo
Classifier: Development Status :: 5 - Production/Stable
Classifier: Framework :: Django
Classifier: Framework :: Django :: 6.0
Classifier: Intended Audience :: Developers
Classifier: License :: OSI Approved :: Apache Software License
Classifier: Operating System :: OS Independent
Classifier: Programming Language :: Python :: 3
Classifier: Programming Language :: Python :: 3 :: Only
Classifier: Programming Language :: Python :: 3.12
Classifier: Programming Language :: Python :: 3.13
Classifier: Programming Language :: Python :: 3.14
Requires-Python: >=3.12
Requires-Dist: django<6.1,>=6.0
Requires-Dist: pymongo<5.0,>=4.7
Provides-Extra: docs
Requires-Dist: furo>=2025.7.19; extra == 'docs'
Requires-Dist: sphinx-copybutton; extra == 'docs'
Requires-Dist: sphinx>=7; extra == 'docs'
